CHANGELOG.md
CONTRIBUTORS.md
cement-3.0.14.dist-info/METADATA
cement-3.0.14.dist-info/WHEEL
cement-3.0.14.dist-info/entry_points.txt
cement-3.0.14.dist-info/licenses/LICENSE
cement/__init__.py
cement/cli/__init__.py
cement/cli/controllers/__init__.py
cement/cli/controllers/base.py
cement/cli/main.py
cement/cli/templates/__init__.py
cement/cli/templates/generate/extension/.generate.yml
cement/cli/templates/generate/extension/ext_{{ label }}.py
cement/cli/templates/generate/plugin/.generate.yml
cement/cli/templates/generate/plugin/{{ label }}/__init__.py
cement/cli/templates/generate/plugin/{{ label }}/controllers/__init__.py
cement/cli/templates/generate/plugin/{{ label }}/controllers/{{ label }}.py
cement/cli/templates/generate/plugin/{{ label }}/templates/__init__.py
cement/cli/templates/generate/plugin/{{ label }}/templates/plugins/{{ label }}/command1.jinja2
cement/cli/templates/generate/project/.generate.yml
cement/cli/templates/generate/project/.gitignore
cement/cli/templates/generate/project/CHANGELOG.md
cement/cli/templates/generate/project/Dockerfile
cement/cli/templates/generate/project/LICENSE.md
cement/cli/templates/generate/project/MANIFEST.in
cement/cli/templates/generate/project/Makefile
cement/cli/templates/generate/project/README.md
cement/cli/templates/generate/project/config/{{ label }}.yml.example
cement/cli/templates/generate/project/docs/.gitkeep
cement/cli/templates/generate/project/requirements-dev.txt
cement/cli/templates/generate/project/requirements.txt
cement/cli/templates/generate/project/setup.cfg
cement/cli/templates/generate/project/setup.py
cement/cli/templates/generate/project/tests/conftest.py
cement/cli/templates/generate/project/tests/test_{{ label }}.py
cement/cli/templates/generate/project/{{ label }}/__init__.py
cement/cli/templates/generate/project/{{ label }}/controllers/__init__.py
cement/cli/templates/generate/project/{{ label }}/controllers/base.py
cement/cli/templates/generate/project/{{ label }}/core/__init__.py
cement/cli/templates/generate/project/{{ label }}/core/exc.py
cement/cli/templates/generate/project/{{ label }}/core/version.py
cement-3.0.14.dist-info/RECORD
