Metadata-Version: 2.1
Name: cement
Version: 3.0.14
Summary: Application Framework for Python
Keywords: python,module,cli framework
Author-Email: "Data Folk Labs, LLC" <derks@datafolklabs.com>
License: 
Classifier: Programming Language :: Python :: 3
Classifier: License :: OSI Approved :: BSD License
Project-URL: homepage, https://builtoncement.com
Project-URL: documentation, https://docs.builtoncement.com
Project-URL: repository, https://github.com/datafolklabs/cement
Requires-Python: >=3.8
Provides-Extra: alarm
Provides-Extra: argparse
Provides-Extra: colorlog
Requires-Dist: colorlog; extra == "colorlog"
Provides-Extra: configparser
Provides-Extra: daemon
Provides-Extra: docs
Requires-Dist: sphinx; extra == "docs"
Requires-Dist: sphinx_rtd_theme; extra == "docs"
Requires-Dist: guzzle_sphinx_theme; extra == "docs"
Requires-Dist: sphinxcontrib-napoleon; extra == "docs"
Provides-Extra: dummy
Provides-Extra: generate
Requires-Dist: pyYaml; extra == "generate"
Provides-Extra: jinja2
Requires-Dist: jinja2; extra == "jinja2"
Provides-Extra: json
Provides-Extra: logging
Provides-Extra: memcached
Requires-Dist: pylibmc; extra == "memcached"
Provides-Extra: mustache
Requires-Dist: pystache; extra == "mustache"
Provides-Extra: plugin
Provides-Extra: print
Provides-Extra: redis
Requires-Dist: redis; extra == "redis"
Provides-Extra: scrub
Provides-Extra: smtp
Provides-Extra: tabulate
Requires-Dist: tabulate; extra == "tabulate"
Provides-Extra: watchdog
Requires-Dist: watchdog; extra == "watchdog"
Provides-Extra: yaml
Requires-Dist: pyYaml; extra == "yaml"
Provides-Extra: cli
Requires-Dist: cement[jinja2,yaml]; extra == "cli"
